[
  {
    "raw case info": "Gustafson v. Florida, 414 U.S. 260 (1973).",
    "name": "Gustafson v. Florida",
    "citation": "414 U.S. 260",
    "year": "1973",
    "url": "https://tile.loc.gov/storage-services/service/ll/usrep/usrep414/usrep414260/usrep414260.pdf"
  },
  {
    "raw case info": "NLRB v. Savair Mfg. Co., 414 U.S. 270 (1973).",
    "name": "NLRB v. Savair Mfg. Co.",
    "citation": "414 U.S. 270",
    "year": "1973",
    "url": "https://tile.loc.gov/storage-services/service/ll/usrep/usrep414/usrep414270/usrep414270.pdf"
  },
  {
    "raw case info": "Zahn v. International Paper Co., 414 U.S. 291 (1973).",
    "name": "Zahn v. International Paper Co.",
    "citation": "414 U.S. 291",
    "year": "1973",
    "url": "https://tile.loc.gov/storage-services/service/ll/usrep/usrep414/usrep414291/usrep414291.pdf"
  },
  {
    "raw case info": "Bonelli Cattle Co. v. Arizona, 414 U.S. 313 (1973).",
    "name": "Bonelli Cattle Co. v. Arizona",
    "citation": "414 U.S. 313",
    "year": "1973",
    "url": "https://tile.loc.gov/storage-services/service/ll/usrep/usrep414/usrep414313/usrep414313.pdf"
  },
  {
    "raw case info": "United States v. Calandra, 414 U.S. 338 (1974).",
    "name": "United States v. Calandra",
    "citation": "414 U.S. 338",
    "year": "1974",
    "url": "https://tile.loc.gov/storage-services/service/ll/usrep/usrep414/usrep414338/usrep414338.pdf"
  },
  {
    "raw case info": "Gateway Coal Co. v. Mine Workers, 414 U.S. 368 (1974).",
    "name": "Gateway Coal Co. v. Mine Workers",
    "citation": "414 U.S. 368",
    "year": "1974",
    "url": "https://tile.loc.gov/storage-services/service/ll/usrep/usrep414/usrep414368/usrep414368.pdf"
  },
  {
    "raw case info": "United States v. Maze, 414 U.S. 395 (1974).",
    "name": "United States v. Maze",
    "citation": "414 U.S. 395",
    "year": "1974",
    "url": "https://tile.loc.gov/storage-services/service/ll/usrep/usrep414/usrep414395/usrep414395.pdf"
  },
  {
    "raw case info": "Mitchell v. W. T. Grant Co., 416 U.S. 600 (1974).",
    "name": "Mitchell v. W. T. Grant Co.",
    "citation": "416 U.S. 600",
    "year": "1974",
    "url": "https://tile.loc.gov/storage-services/service/ll/usrep/usrep416/usrep416600/usrep416600.pdf"
  },
  {
    "raw case info": "Donnelly v. DeChristoforo, 416 U.S. 637 (1974).",
    "name": "Donnelly v. DeChristoforo",
    "citation": "416 U.S. 637",
    "year": "1974",
    "url": "https://tile.loc.gov/storage-services/service/ll/usrep/usrep416/usrep416637/usrep416637.pdf"
  },
  {
    "raw case info": "Calero-Toledo v. Pearson Yacht Leasing Co., 416 U.S. 663 (1974).",
    "name": "Calero-Toledo v. Pearson Yacht Leasing Co.",
    "citation": "416 U.S. 663",
    "year": "1974",
    "url": "https://tile.loc.gov/storage-services/service/ll/usrep/usrep416/usrep416663/usrep416663.pdf"
  },
  {
    "raw case info": "Commissioner v. \"Americans United\" Inc., 416 U.S. 752 (1974).",
    "name": "Commissioner v. \"Americans United\" Inc.",
    "citation": "416 U.S. 752",
    "year": "1974",
    "url": "https://tile.loc.gov/storage-services/service/ll/usrep/usrep416/usrep416752/usrep416752.pdf"
  },
  {
    "raw case info": "Air Pollution Variance Bd. v. Western Alfalfa, 416 U.S. 861 (1974).",
    "name": "Air Pollution Variance Bd. v. Western Alfalfa",
    "citation": "416 U.S. 861",
    "year": "1974",
    "url": "https://tile.loc.gov/storage-services/service/ll/usrep/usrep416/usrep416861/usrep416861.pdf"
  },
  {
    "raw case info": "Warm Springs Dam Task Force v. Gribble, 417 U.S. 1301 (1974).",
    "name": "Warm Springs Dam Task Force v. Gribble",
    "citation": "417 U.S. 1301",
    "year": "1974",
    "url": "https://tile.loc.gov/storage-services/service/ll/usrep/usrep417/usrep4171301/usrep4171301.pdf"
  },
  {
    "raw case info": "Commissioner v. Nat. Alfalfa Dehydrating, 417 U.S. 134 (1974).",
    "name": "Commissioner v. Nat. Alfalfa Dehydrating",
    "citation": "417 U.S. 134",
    "year": "1974",
    "url": "https://tile.loc.gov/storage-services/service/ll/usrep/usrep417/usrep417134/usrep417134.pdf"
  },
  {
    "raw case info": "Eisen v. Carlisle &amp; Jacquelin, 417 U.S. 156 (1974).",
    "name": "Eisen v. Carlisle &amp; Jacquelin",
    "citation": "417 U.S. 156",
    "year": "1974",
    "url": "https://tile.loc.gov/storage-services/service/ll/usrep/usrep417/usrep417156/usrep417156.pdf"
  },
  {
    "raw case info": "Holder v. Banks, 417 U.S. 187 (1974).",
    "name": "Holder v. Banks",
    "citation": "417 U.S. 187",
    "year": "1974",
    "url": "https://tile.loc.gov/storage-services/service/ll/usrep/usrep417/usrep417187/usrep417187.pdf"
  },
  {
    "raw case info": "Corning Glass Works v. Brennan, 417 U.S. 188 (1974).",
    "name": "Corning Glass Works v. Brennan",
    "citation": "417 U.S. 188",
    "year": "1974",
    "url": "https://tile.loc.gov/storage-services/service/ll/usrep/usrep417/usrep417188/usrep417188.pdf"
  },
  {
    "raw case info": "Anderson v. United States, 417 U.S. 211 (1974).",
    "name": "Anderson v. United States",
    "citation": "417 U.S. 211",
    "year": "1974",
    "url": "https://tile.loc.gov/storage-services/service/ll/usrep/usrep417/usrep417211/usrep417211.pdf"
  },
  {
    "raw case info": "Howard Johnson Co. v. Hotel Employees, 417 U.S. 249 (1974).",
    "name": "Howard Johnson Co. v. Hotel Employees",
    "citation": "417 U.S. 249",
    "year": "1974",
    "url": "https://tile.loc.gov/storage-services/service/ll/usrep/usrep417/usrep417249/usrep417249.pdf"
  },
  {
    "raw case info": "Vermont v. New York, 417 U.S. 270 (1974).",
    "name": "Vermont v. New York",
    "citation": "417 U.S. 270",
    "year": "1974",
    "url": "https://tile.loc.gov/storage-services/service/ll/usrep/usrep417/usrep417270/usrep417270.pdf"
  },
  {
    "raw case info": "Mobil Oil Corp. v. FPC, 417 U.S. 283 (1974).",
    "name": "Mobil Oil Corp. v. FPC",
    "citation": "417 U.S. 283",
    "year": "1974",
    "url": "https://tile.loc.gov/storage-services/service/ll/usrep/usrep417/usrep417283/usrep417283.pdf"
  },
  {
    "raw case info": "Davis v. United States, 417 U.S. 333 (1974).",
    "name": "Davis v. United States",
    "citation": "417 U.S. 333",
    "year": "1974",
    "url": "https://tile.loc.gov/storage-services/service/ll/usrep/usrep417/usrep417333/usrep417333.pdf"
  },
  {
    "raw case info": "Pittsburgh v. Alco Parking Corp., 417 U.S. 369 (1974).",
    "name": "Pittsburgh v. Alco Parking Corp.",
    "citation": "417 U.S. 369",
    "year": "1974",
    "url": "https://tile.loc.gov/storage-services/service/ll/usrep/usrep417/usrep417369/usrep417369.pdf"
  },
  {
    "raw case info": "FPC v. Texaco Inc., 417 U.S. 380 (1974).",
    "name": "FPC v. Texaco Inc.",
    "citation": "417 U.S. 380",
    "year": "1974",
    "url": "https://tile.loc.gov/storage-services/service/ll/usrep/usrep417/usrep417380/usrep417380.pdf"
  },
  {
    "raw case info": "Wheeler v. Barrera, 417 U.S. 402 (1974).",
    "name": "Wheeler v. Barrera",
    "citation": "417 U.S. 402",
    "year": "1974",
    "url": "https://tile.loc.gov/storage-services/service/ll/usrep/usrep417/usrep417402/usrep417402.pdf"
  },
  {
    "raw case info": "Michigan v. Tucker, 417 U.S. 433 (1974).",
    "name": "Michigan v. Tucker",
    "citation": "417 U.S. 433",
    "year": "1974",
    "url": "https://tile.loc.gov/storage-services/service/ll/usrep/usrep417/usrep417433/usrep417433.pdf"
  },
  {
    "raw case info": "Baker v. Gold Seal Liquors, 417 U.S. 467 (1974).",
    "name": "Baker v. Gold Seal Liquors",
    "citation": "417 U.S. 467",
    "year": "1974",
    "url": "https://tile.loc.gov/storage-services/service/ll/usrep/usrep417/usrep417467/usrep417467.pdf"
  },
  {
    "raw case info": "Geduldig v. Aiello, 417 U.S. 484 (1974).",
    "name": "Geduldig v. Aiello",
    "citation": "417 U.S. 484",
    "year": "1974",
    "url": "https://tile.loc.gov/storage-services/service/ll/usrep/usrep417/usrep417484/usrep417484.pdf"
  },
  {
    "raw case info": "Scherk v. Alberto-Culver Co., 417 U.S. 506 (1974).",
    "name": "Scherk v. Alberto-Culver Co.",
    "citation": "417 U.S. 506",
    "year": "1974",
    "url": "https://tile.loc.gov/storage-services/service/ll/usrep/usrep417/usrep417506/usrep417506.pdf"
  },
  {
    "raw case info": "Morton v. Mancari, 417 U.S. 535 (1974).",
    "name": "Morton v. Mancari",
    "citation": "417 U.S. 535",
    "year": "1974",
    "url": "https://tile.loc.gov/storage-services/service/ll/usrep/usrep417/usrep417535/usrep417535.pdf"
  },
  {
    "raw case info": "Gilmore v. City of Montgomery, 417 U.S. 556 (1974).",
    "name": "Gilmore v. City of Montgomery",
    "citation": "417 U.S. 556",
    "year": "1974",
    "url": "https://tile.loc.gov/storage-services/service/ll/usrep/usrep417/usrep417556/usrep417556.pdf"
  },
  {
    "raw case info": "Cardwell v. Lewis, 417 U.S. 583 (1974).",
    "name": "Cardwell v. Lewis",
    "citation": "417 U.S. 583",
    "year": "1974",
    "url": "https://tile.loc.gov/storage-services/service/ll/usrep/usrep417/usrep417583/usrep417583.pdf"
  },
  {
    "raw case info": "Ross v. Moffitt, 417 U.S. 600 (1974).",
    "name": "Ross v. Moffitt",
    "citation": "417 U.S. 600",
    "year": "1974",
    "url": "https://tile.loc.gov/storage-services/service/ll/usrep/usrep417/usrep417600/usrep417600.pdf"
  },
  {
    "raw case info": "Moody v. Albemarle Paper Co., 417 U.S. 622 (1974).",
    "name": "Moody v. Albemarle Paper Co.",
    "citation": "417 U.S. 622",
    "year": "1974",
    "url": "https://tile.loc.gov/storage-services/service/ll/usrep/usrep417/usrep417622/usrep417622.pdf"
  },
  {
    "raw case info": "Jimenez v. Weinberger, 417 U.S. 628 (1974).",
    "name": "Jimenez v. Weinberger",
    "citation": "417 U.S. 628",
    "year": "1974",
    "url": "https://tile.loc.gov/storage-services/service/ll/usrep/usrep417/usrep417628/usrep417628.pdf"
  },
  {
    "raw case info": "Kokoszka v. Belford, 417 U.S. 642 (1974).",
    "name": "Kokoszka v. Belford",
    "citation": "417 U.S. 642",
    "year": "1974",
    "url": "https://tile.loc.gov/storage-services/service/ll/usrep/usrep417/usrep417642/usrep417642.pdf"
  },
  {
    "raw case info": "Warden v. Marrero, 417 U.S. 653 (1974).",
    "name": "Warden v. Marrero",
    "citation": "417 U.S. 653",
    "year": "1974",
    "url": "https://tile.loc.gov/storage-services/service/ll/usrep/usrep417/usrep417653/usrep417653.pdf"
  },
  {
    "raw case info": "Central Tablet Mfg. Co. v. United States, 417 U.S. 673 (1974).",
    "name": "Central Tablet Mfg. Co. v. United States",
    "citation": "417 U.S. 673",
    "year": "1974",
    "url": "https://tile.loc.gov/storage-services/service/ll/usrep/usrep417/usrep417673/usrep417673.pdf"
  },
  {
    "raw case info": "Bangor Punta Operations, Inc. v. Bangor &amp; A. R. Co., 417 U.S. 703 (1974).",
    "name": "Bangor Punta Operations, Inc. v. Bangor &amp; A. R. Co.",
    "citation": "417 U.S. 703",
    "year": "1974",
    "url": "https://tile.loc.gov/storage-services/service/ll/usrep/usrep417/usrep417703/usrep417703.pdf"
  },
  {
    "raw case info": "Parker v. Levy, 417 U.S. 733 (1974).",
    "name": "Parker v. Levy",
    "citation": "417 U.S. 733",
    "year": "1974",
    "url": "https://tile.loc.gov/storage-services/service/ll/usrep/usrep417/usrep417733/usrep417733.pdf"
  },
  {
    "raw case info": "Florida Power &amp; Light v. Electrical Workers, 417 U.S. 790 (1974).",
    "name": "Florida Power &amp; Light v. Electrical Workers",
    "citation": "417 U.S. 790",
    "year": "1974",
    "url": "https://tile.loc.gov/storage-services/service/ll/usrep/usrep417/usrep417790/usrep417790.pdf"
  },
  {
    "raw case info": "Pell v. Procunier, 417 U.S. 817 (1973).",
    "name": "Pell v. Procunier",
    "citation": "417 U.S. 817",
    "year": "1973",
    "url": "https://tile.loc.gov/storage-services/service/ll/usrep/usrep417/usrep417817/usrep417817.pdf"
  },
  {
    "raw case info": "Saxbe v. Washington Post Co., 417 U.S. 843 (1974).",
    "name": "Saxbe v. Washington Post Co.",
    "citation": "417 U.S. 843",
    "year": "1974",
    "url": "https://tile.loc.gov/storage-services/service/ll/usrep/usrep417/usrep417843/usrep417843.pdf"
  },
  {
    "raw case info": "Commissioner v. Idaho Power Co., 418 U.S. 1 (1974).",
    "name": "Commissioner v. Idaho Power Co.",
    "citation": "418 U.S. 1",
    "year": "1974",
    "url": "https://tile.loc.gov/storage-services/service/ll/usrep/usrep418/usrep418001/usrep418001.pdf"
  },
  {
    "raw case info": "Richardson v. Ramirez, 418 U.S. 24 (1974).",
    "name": "Richardson v. Ramirez",
    "citation": "418 U.S. 24",
    "year": "1974",
    "url": "https://tile.loc.gov/storage-services/service/ll/usrep/usrep418/usrep418024/usrep418024.pdf"
  },
  {
    "raw case info": "Hamling v. United States, 418 U.S. 87 (1974).",
    "name": "Hamling v. United States",
    "citation": "418 U.S. 87",
    "year": "1974",
    "url": "https://tile.loc.gov/storage-services/service/ll/usrep/usrep418/usrep418087/usrep418087.pdf"
  },
  {
    "raw case info": "In re Grand Jury Proceedings (Lewis, Applicant), 418 U.S. 1301 (1974).",
    "name": "In re Grand Jury Proceedings (Lewis, Applicant)",
    "citation": "418 U.S. 1301",
    "year": "1974",
    "url": "https://tile.loc.gov/storage-services/service/ll/usrep/usrep418/usrep4181301/usrep4181301.pdf"
  },
  {
    "raw case info": "Jenkins v. Georgia, 418 U.S. 153 (1974).",
    "name": "Jenkins v. Georgia",
    "citation": "418 U.S. 153",
    "year": "1974",
    "url": "https://tile.loc.gov/storage-services/service/ll/usrep/usrep418/usrep418153/usrep418153.pdf"
  },
  {
    "raw case info": "United States v. Richardson, 418 U.S. 166 (1974).",
    "name": "United States v. Richardson",
    "citation": "418 U.S. 166",
    "year": "1974",
    "url": "https://tile.loc.gov/storage-services/service/ll/usrep/usrep418/usrep418166/usrep418166.pdf"
  },
  {
    "raw case info": "Schlesinger v. Reservists to Stop the War, 418 U.S. 208 (1973).",
    "name": "Schlesinger v. Reservists to Stop the War",
    "citation": "418 U.S. 208",
    "year": "1973",
    "url": "https://tile.loc.gov/storage-services/service/ll/usrep/usrep418/usrep418208/usrep418208.pdf"
  },
  {
    "raw case info": "Miami Herald Publishing Co. v. Tornillo, 418 U.S. 241 (1974).",
    "name": "Miami Herald Publishing Co. v. Tornillo",
    "citation": "418 U.S. 241",
    "year": "1974",
    "url": "https://tile.loc.gov/storage-services/service/ll/usrep/usrep418/usrep418241/usrep418241.pdf"
  },
  {
    "raw case info": "Letter Carriers v. Austin, 418 U.S. 264 (1974).",
    "name": "Letter Carriers v. Austin",
    "citation": "418 U.S. 264",
    "year": "1974",
    "url": "https://tile.loc.gov/storage-services/service/ll/usrep/usrep418/usrep418264/usrep418264.pdf"
  },
  {
    "raw case info": "Lehman v. City of Shaker Heights, 418 U.S. 298 (1974).",
    "name": "Lehman v. City of Shaker Heights",
    "citation": "418 U.S. 298",
    "year": "1974",
    "url": "https://tile.loc.gov/storage-services/service/ll/usrep/usrep418/usrep418298/usrep418298.pdf"
  },
  {
    "raw case info": "Gertz v. Robert Welch, Inc., 418 U.S. 323 (1974).",
    "name": "Gertz v. Robert Welch, Inc.",
    "citation": "418 U.S. 323",
    "year": "1974",
    "url": "https://tile.loc.gov/storage-services/service/ll/usrep/usrep418/usrep418323/usrep418323.pdf"
  },
  {
    "raw case info": "Spence v. Washington, 418 U.S. 405 (1974).",
    "name": "Spence v. Washington",
    "citation": "418 U.S. 405",
    "year": "1974",
    "url": "https://tile.loc.gov/storage-services/service/ll/usrep/usrep418/usrep418405/usrep418405.pdf"
  },
  {
    "raw case info": "Dorszynski v. United States, 418 U.S. 424 (1974).",
    "name": "Dorszynski v. United States",
    "citation": "418 U.S. 424",
    "year": "1974",
    "url": "https://tile.loc.gov/storage-services/service/ll/usrep/usrep418/usrep418424/usrep418424.pdf"
  },
  {
    "raw case info": "Wingo v. Wedding, 418 U.S. 461 (1974).",
    "name": "Wingo v. Wedding",
    "citation": "418 U.S. 461",
    "year": "1974",
    "url": "https://tile.loc.gov/storage-services/service/ll/usrep/usrep418/usrep418461/usrep418461.pdf"
  },
  {
    "raw case info": "Taylor v. Hayes, 418 U.S. 488 (1974).",
    "name": "Taylor v. Hayes",
    "citation": "418 U.S. 488",
    "year": "1974",
    "url": "https://tile.loc.gov/storage-services/service/ll/usrep/usrep418/usrep418488/usrep418488.pdf"
  },
  {
    "raw case info": "Codispoti v. Pennsylvania, 418 U.S. 506 (1973).",
    "name": "Codispoti v. Pennsylvania",
    "citation": "418 U.S. 506",
    "year": "1973",
    "url": "https://tile.loc.gov/storage-services/service/ll/usrep/usrep418/usrep418506/usrep418506.pdf"
  },
  {
    "raw case info": "Wolff v. McDonnell, 418 U.S. 539 (1974).",
    "name": "Wolff v. McDonnell",
    "citation": "418 U.S. 539",
    "year": "1974",
    "url": "https://tile.loc.gov/storage-services/service/ll/usrep/usrep418/usrep418539/usrep418539.pdf"
  },
  {
    "raw case info": "United States v. Marine Bancorporation, 418 U.S. 602 (1974).",
    "name": "United States v. Marine Bancorporation",
    "citation": "418 U.S. 602",
    "year": "1974",
    "url": "https://tile.loc.gov/storage-services/service/ll/usrep/usrep418/usrep418602/usrep418602.pdf"
  },
  {
    "raw case info": "United States v. Connecticut National Bank, 418 U.S. 656 (1974).",
    "name": "United States v. Connecticut National Bank",
    "citation": "418 U.S. 656",
    "year": "1974",
    "url": "https://tile.loc.gov/storage-services/service/ll/usrep/usrep418/usrep418656/usrep418656.pdf"
  },
  {
    "raw case info": "Snow v. Commissioner, 416 U.S. 500 (1974).",
    "name": "Snow v. Commissioner",
    "citation": "416 U.S. 500",
    "year": "1974",
    "url": "https://tile.loc.gov/storage-services/service/ll/usrep/usrep416/usrep416500/usrep416500.pdf"
  },
  {
    "raw case info": "United States v. Giordano, 416 U.S. 505 (1974).",
    "name": "United States v. Giordano",
    "citation": "416 U.S. 505",
    "year": "1974",
    "url": "https://tile.loc.gov/storage-services/service/ll/usrep/usrep416/usrep416505/usrep416505.pdf"
  },
  {
    "raw case info": "United States v. Chavez, 416 U.S. 562 (1974).",
    "name": "United States v. Chavez",
    "citation": "416 U.S. 562",
    "year": "1974",
    "url": "https://tile.loc.gov/storage-services/service/ll/usrep/usrep416/usrep416562/usrep416562.pdf"
  },
  {
    "raw case info": "Beasley v. Food Fair of North Carolina, 416 U.S. 653 (1974).",
    "name": "Beasley v. Food Fair of North Carolina",
    "citation": "416 U.S. 653",
    "year": "1974",
    "url": "https://tile.loc.gov/storage-services/service/ll/usrep/usrep416/usrep416653/usrep416653.pdf"
  },
  {
    "raw case info": "Bradley v. Richmond School Board, 416 U.S. 696 (1974).",
    "name": "Bradley v. Richmond School Board",
    "citation": "416 U.S. 696",
    "year": "1974",
    "url": "https://tile.loc.gov/storage-services/service/ll/usrep/usrep416/usrep416696/usrep416696.pdf"
  },
  {
    "raw case info": "Bob Jones University v. Simon, 416 U.S. 725 (1974).",
    "name": "Bob Jones University v. Simon",
    "citation": "416 U.S. 725",
    "year": "1974",
    "url": "https://tile.loc.gov/storage-services/service/ll/usrep/usrep416/usrep416725/usrep416725.pdf"
  },
  {
    "raw case info": "Dillard v. Virginia Industrial Comm'n, 416 U.S. 783 (1974).",
    "name": "Dillard v. Virginia Industrial Comm'n",
    "citation": "416 U.S. 783",
    "year": "1974",
    "url": "https://tile.loc.gov/storage-services/service/ll/usrep/usrep416/usrep416783/usrep416783.pdf"
  },
  {
    "raw case info": "Allee v. Medrano, 416 U.S. 802 (1974).",
    "name": "Allee v. Medrano",
    "citation": "416 U.S. 802",
    "year": "1974",
    "url": "https://tile.loc.gov/storage-services/service/ll/usrep/usrep416/usrep416802/usrep416802.pdf"
  },
  {
    "raw case info": "NLRB v. Food Store Employees, 417 U.S. 1 (1974).",
    "name": "NLRB v. Food Store Employees",
    "citation": "417 U.S. 1",
    "year": "1974",
    "url": "https://tile.loc.gov/storage-services/service/ll/usrep/usrep417/usrep417001/usrep417001.pdf"
  },
  {
    "raw case info": "William E. Arnold Co. v. Carpenters, 417 U.S. 12 (1974).",
    "name": "William E. Arnold Co. v. Carpenters",
    "citation": "417 U.S. 12",
    "year": "1974",
    "url": "https://tile.loc.gov/storage-services/service/ll/usrep/usrep417/usrep417012/usrep417012.pdf"
  },
  {
    "raw case info": "Blackledge v. Perry, 417 U.S. 21 (1974).",
    "name": "Blackledge v. Perry",
    "citation": "417 U.S. 21",
    "year": "1974",
    "url": "https://tile.loc.gov/storage-services/service/ll/usrep/usrep417/usrep417021/usrep417021.pdf"
  },
  {
    "raw case info": "Fuller v. Oregon, 417 U.S. 40 (1974).",
    "name": "Fuller v. Oregon",
    "citation": "417 U.S. 40",
    "year": "1974",
    "url": "https://tile.loc.gov/storage-services/service/ll/usrep/usrep417/usrep417040/usrep417040.pdf"
  },
  {
    "raw case info": "Kosydar v. National Cash Register Co., 417 U.S. 62 (1974).",
    "name": "Kosydar v. National Cash Register Co.",
    "citation": "417 U.S. 62",
    "year": "1974",
    "url": "https://tile.loc.gov/storage-services/service/ll/usrep/usrep417/usrep417062/usrep417062.pdf"
  },
  {
    "raw case info": "Cass v. United States, 417 U.S. 72 (1974).",
    "name": "Cass v. United States",
    "citation": "417 U.S. 72",
    "year": "1974",
    "url": "https://tile.loc.gov/storage-services/service/ll/usrep/usrep417/usrep417072/usrep417072.pdf"
  },
  {
    "raw case info": "Bellis v. United States, 417 U.S. 85 (1974).",
    "name": "Bellis v. United States",
    "citation": "417 U.S. 85",
    "year": "1974",
    "url": "https://tile.loc.gov/storage-services/service/ll/usrep/usrep417/usrep417085/usrep417085.pdf"
  },
  {
    "raw case info": "Cooper Stevedoring Co. v. Kopke, Inc., 417 U.S. 106 (1974).",
    "name": "Cooper Stevedoring Co. v. Kopke, Inc.",
    "citation": "417 U.S. 106",
    "year": "1974",
    "url": "https://tile.loc.gov/storage-services/service/ll/usrep/usrep417/usrep417106/usrep417106.pdf"
  },
  {
    "raw case info": "F.D. Rich Co. v. Industrial Lumber Co., 417 U.S. 116 (1974).",
    "name": "F.D. Rich Co. v. Industrial Lumber Co.",
    "citation": "417 U.S. 116",
    "year": "1974",
    "url": "https://tile.loc.gov/storage-services/service/ll/usrep/usrep417/usrep417116/usrep417116.pdf"
  },
  {
    "raw case info": "Gerstein v. Coe, 417 U.S. 279 (1974).",
    "name": "Gerstein v. Coe",
    "citation": "417 U.S. 279",
    "year": "1974",
    "url": "https://tile.loc.gov/storage-services/service/ll/usrep/usrep417/usrep417279/usrep417279.pdf"
  },
  {
    "raw case info": "Poe v. Gerstein, 417 U.S. 281 (1974).",
    "name": "Poe v. Gerstein",
    "citation": "417 U.S. 281",
    "year": "1974",
    "url": "https://tile.loc.gov/storage-services/service/ll/usrep/usrep417/usrep417281/usrep417281.pdf"
  },
  {
    "raw case info": "Secretary of the Navy v. Avrech, 418 U.S. 676 (1974).",
    "name": "Secretary of the Navy v. Avrech",
    "citation": "418 U.S. 676",
    "year": "1974",
    "url": "https://tile.loc.gov/storage-services/service/ll/usrep/usrep418/usrep418676/usrep418676.pdf"
  },
  {
    "raw case info": "United States v. Nixon, 418 U.S. 683 (1974).",
    "name": "United States v. Nixon",
    "citation": "418 U.S. 683",
    "year": "1974",
    "url": "https://tile.loc.gov/storage-services/service/ll/usrep/usrep418/usrep418683/usrep418683.pdf"
  },
  {
    "raw case info": "Milliken v. Bradley, 418 U.S. 717 (1974).",
    "name": "Milliken v. Bradley",
    "citation": "418 U.S. 717",
    "year": "1974",
    "url": "https://tile.loc.gov/storage-services/service/ll/usrep/usrep418/usrep418717/usrep418717.pdf"
  },
  {
    "raw case info": "Marshall v. United States, 414 U.S. 417 (1974).",
    "name": "Marshall v. United States",
    "citation": "414 U.S. 417",
    "year": "1974",
    "url": "https://tile.loc.gov/storage-services/service/ll/usrep/usrep414/usrep414417/usrep414417.pdf"
  },
  {
    "raw case info": "Communist Party of Indiana v. Whitcomb, 414 U.S. 441 (1974).",
    "name": "Communist Party of Indiana v. Whitcomb",
    "citation": "414 U.S. 441",
    "year": "1974",
    "url": "https://tile.loc.gov/storage-services/service/ll/usrep/usrep414/usrep414441/usrep414441.pdf"
  },
  {
    "raw case info": "Passenger Corp. v. Passenger Assn., 414 U.S. 453 (1974).",
    "name": "Passenger Corp. v. Passenger Assn.",
    "citation": "414 U.S. 453",
    "year": "1974",
    "url": "https://tile.loc.gov/storage-services/service/ll/usrep/usrep414/usrep414453/usrep414453.pdf"
  },
  {
    "raw case info": "Schmidt v. Lessard, 414 U.S. 473 (1974).",
    "name": "Schmidt v. Lessard",
    "citation": "414 U.S. 473",
    "year": "1974",
    "url": "https://tile.loc.gov/storage-services/service/ll/usrep/usrep414/usrep414473/usrep414473.pdf"
  },
  {
    "raw case info": "Vachon v. New Hampshire, 414 U.S. 478 (1974).",
    "name": "Vachon v. New Hampshire",
    "citation": "414 U.S. 478",
    "year": "1974",
    "url": "https://tile.loc.gov/storage-services/service/ll/usrep/usrep414/usrep414478/usrep414478.pdf"
  },
  {
    "raw case info": "O'Shea v. Littleton, 414 U.S. 488 (1974).",
    "name": "O'Shea v. Littleton",
    "citation": "414 U.S. 488",
    "year": "1974",
    "url": "https://tile.loc.gov/storage-services/service/ll/usrep/usrep414/usrep414488/usrep414488.pdf"
  },
  {
    "raw case info": "Spomer v. Littleton, 414 U.S. 514 (1974).",
    "name": "Spomer v. Littleton",
    "citation": "414 U.S. 514",
    "year": "1974",
    "url": "https://tile.loc.gov/storage-services/service/ll/usrep/usrep414/usrep414514/usrep414514.pdf"
  },
  {
    "raw case info": "O'Brien v. Skinner, 414 U.S. 524 (1974).",
    "name": "O'Brien v. Skinner",
    "citation": "414 U.S. 524",
    "year": "1974",
    "url": "https://tile.loc.gov/storage-services/service/ll/usrep/usrep414/usrep414524/usrep414524.pdf"
  },
  {
    "raw case info": "American Pipe &amp; Construction Co. v. Utah, 414 U.S. 538 (1974).",
    "name": "American Pipe &amp; Construction Co. v. Utah",
    "citation": "414 U.S. 538",
    "year": "1974",
    "url": "https://tile.loc.gov/storage-services/service/ll/usrep/usrep414/usrep414538/usrep414538.pdf"
  },
  {
    "raw case info": "Lau v. Nichols, 414 U.S. 563 (1974).",
    "name": "Lau v. Nichols",
    "citation": "414 U.S. 563",
    "year": "1974",
    "url": "https://tile.loc.gov/storage-services/service/ll/usrep/usrep414/usrep414563/usrep414563.pdf"
  },
  {
    "raw case info": "Sea-Land Services, Inc. v. Gaudet, 414 U.S. 573 (1974).",
    "name": "Sea-Land Services, Inc. v. Gaudet",
    "citation": "414 U.S. 573",
    "year": "1974",
    "url": "https://tile.loc.gov/storage-services/service/ll/usrep/usrep414/usrep414573/usrep414573.pdf"
  },
  {
    "raw case info": "Christian v. New York Department of Labor, 414 U.S. 614 (1974).",
    "name": "Christian v. New York Department of Labor",
    "citation": "414 U.S. 614",
    "year": "1974",
    "url": "https://tile.loc.gov/storage-services/service/ll/usrep/usrep414/usrep414614/usrep414614.pdf"
  },
  {
    "raw case info": "Cleveland Board of Education v. LaFleur, 414 U.S. 632 (1974).",
    "name": "Cleveland Board of Education v. LaFleur",
    "citation": "414 U.S. 632",
    "year": "1974",
    "url": "https://tile.loc.gov/storage-services/service/ll/usrep/usrep414/usrep414632/usrep414632.pdf"
  },
  {
    "raw case info": "Oneida Indian Nation v. County of Oneida, 414 U.S. 661 (1974).",
    "name": "Oneida Indian Nation v. County of Oneida",
    "citation": "414 U.S. 661",
    "year": "1974",
    "url": "https://tile.loc.gov/storage-services/service/ll/usrep/usrep414/usrep414661/usrep414661.pdf"
  },
  {
    "raw case info": "Snider v. All State Administrators, 414 U.S. 685 (1974).",
    "name": "Snider v. All State Administrators",
    "citation": "414 U.S. 685",
    "year": "1974",
    "url": "https://tile.loc.gov/storage-services/service/ll/usrep/usrep414/usrep414685/usrep414685.pdf"
  }
]
