[
  {
    "raw case info": "United States v. Board of Supervisors, 429 U.S. 642 (1977).",
    "name": "United States v. Board of Supervisors",
    "citation": "429 U.S. 642",
    "year": "1977",
    "url": "https://tile.loc.gov/storage-services/service/ll/usrep/usrep429/usrep429642/usrep429642.pdf"
  },
  {
    "raw case info": "Donovan v. Penn Shipping Co., 429 U.S. 648 (1977).",
    "name": "Donovan v. Penn Shipping Co.",
    "citation": "429 U.S. 648",
    "year": "1977",
    "url": "https://tile.loc.gov/storage-services/service/ll/usrep/usrep429/usrep429648/usrep429648.pdf"
  },
  {
    "raw case info": "Concerned Citizens v. Pine Creek District, 429 U.S. 651 (1977).",
    "name": "Concerned Citizens v. Pine Creek District",
    "citation": "429 U.S. 651",
    "year": "1977",
    "url": "https://tile.loc.gov/storage-services/service/ll/usrep/usrep429/usrep429651/usrep429651.pdf"
  },
  {
    "raw case info": "Piper v. Chris-Craft Industries, 430 U.S. 1 (1977).",
    "name": "Piper v. Chris-Craft Industries",
    "citation": "430 U.S. 1",
    "year": "1977",
    "url": "https://tile.loc.gov/storage-services/service/ll/usrep/usrep430/usrep430001/usrep430001.pdf"
  },
  {
    "raw case info": "Delaware Tribal Business Comm v. Weeks, 430 U.S. 73 (1977).",
    "name": "Delaware Tribal Business Comm v. Weeks",
    "citation": "430 U.S. 73",
    "year": "1977",
    "url": "https://tile.loc.gov/storage-services/service/ll/usrep/usrep430/usrep430073/usrep430073.pdf"
  },
  {
    "raw case info": "Califano v. Sanders, 430 U.S. 99 (1977).",
    "name": "Califano v. Sanders",
    "citation": "430 U.S. 99",
    "year": "1977",
    "url": "https://tile.loc.gov/storage-services/service/ll/usrep/usrep430/usrep430099/usrep430099.pdf"
  },
  {
    "raw case info": "E. I. du Pont de Nemours &amp; (and) Co. v. Train, 430 U.S. 112 (1977).",
    "name": "E. I. du Pont de Nemours &amp; (and) Co. v. Train",
    "citation": "430 U.S. 112",
    "year": "1977",
    "url": "https://tile.loc.gov/storage-services/service/ll/usrep/usrep430/usrep430112/usrep430112.pdf"
  },
  {
    "raw case info": "United States v. Florida et al., 430 U.S. 140 (1977).",
    "name": "United States v. Florida et al.",
    "citation": "430 U.S. 140",
    "year": "1977",
    "url": "https://tile.loc.gov/storage-services/service/ll/usrep/usrep430/usrep430140/usrep430140.pdf"
  },
  {
    "raw case info": "Philadelphia v. New Jersey, 430 U.S. 141 (1977).",
    "name": "Philadelphia v. New Jersey",
    "citation": "430 U.S. 141",
    "year": "1977",
    "url": "https://tile.loc.gov/storage-services/service/ll/usrep/usrep430/usrep430141/usrep430141.pdf"
  },
  {
    "raw case info": "United Jewish Organizations v. Carey, 430 U.S. 144 (1977).",
    "name": "United Jewish Organizations v. Carey",
    "citation": "430 U.S. 144",
    "year": "1977",
    "url": "https://tile.loc.gov/storage-services/service/ll/usrep/usrep430/usrep430144/usrep430144.pdf"
  },
  {
    "raw case info": "Marks v. United States, 430 U.S. 188 (1977).",
    "name": "Marks v. United States",
    "citation": "430 U.S. 188",
    "year": "1977",
    "url": "https://tile.loc.gov/storage-services/service/ll/usrep/usrep430/usrep430188/usrep430188.pdf"
  },
  {
    "raw case info": "Califano v. Goldfarb, 430 U.S. 199 (1977).",
    "name": "Califano v. Goldfarb",
    "citation": "430 U.S. 199",
    "year": "1977",
    "url": "https://tile.loc.gov/storage-services/service/ll/usrep/usrep430/usrep430199/usrep430199.pdf"
  },
  {
    "raw case info": "Nolde Bros., Inc. v. Bakery Workers, 430 U.S. 243 (1977).",
    "name": "Nolde Bros., Inc. v. Bakery Workers",
    "citation": "430 U.S. 243",
    "year": "1977",
    "url": "https://tile.loc.gov/storage-services/service/ll/usrep/usrep430/usrep430243/usrep430243.pdf"
  },
  {
    "raw case info": "Lockport v. Citizens for Community Action, 430 U.S. 259 (1977).",
    "name": "Lockport v. Citizens for Community Action",
    "citation": "430 U.S. 259",
    "year": "1977",
    "url": "https://tile.loc.gov/storage-services/service/ll/usrep/usrep430/usrep430259/usrep430259.pdf"
  },
  {
    "raw case info": "Complete Auto Transit, Inc. v. Brady, 430 U.S. 274 (1977).",
    "name": "Complete Auto Transit, Inc. v. Brady",
    "citation": "430 U.S. 274",
    "year": "1977",
    "url": "https://tile.loc.gov/storage-services/service/ll/usrep/usrep430/usrep430274/usrep430274.pdf"
  },
  {
    "raw case info": "Oklahoma Publishing Co. v. District Court, 430 U.S. 308 (1977).",
    "name": "Oklahoma Publishing Co. v. District Court",
    "citation": "430 U.S. 308",
    "year": "1977",
    "url": "https://tile.loc.gov/storage-services/service/ll/usrep/usrep430/usrep430308/usrep430308.pdf"
  },
  {
    "raw case info": "Califano v. Webster, 430 U.S. 313 (1977).",
    "name": "Califano v. Webster",
    "citation": "430 U.S. 313",
    "year": "1977",
    "url": "https://tile.loc.gov/storage-services/service/ll/usrep/usrep430/usrep430313/usrep430313.pdf"
  },
  {
    "raw case info": "United States v. Larionoff, 431 U.S. 864 (1977).",
    "name": "United States v. Larionoff",
    "citation": "431 U.S. 864",
    "year": "1977",
    "url": "https://tile.loc.gov/storage-services/service/ll/usrep/usrep431/usrep431864/usrep431864.pdf"
  },
  {
    "raw case info": "Nyquist v. Mauclet, 432 U.S. 1 (1977).",
    "name": "Nyquist v. Mauclet",
    "citation": "432 U.S. 1",
    "year": "1977",
    "url": "https://tile.loc.gov/storage-services/service/ll/usrep/usrep432/usrep432001/usrep432001.pdf"
  },
  {
    "raw case info": "Lee v. United States, 432 U.S. 23 (1977).",
    "name": "Lee v. United States",
    "citation": "432 U.S. 23",
    "year": "1977",
    "url": "https://tile.loc.gov/storage-services/service/ll/usrep/usrep432/usrep432023/usrep432023.pdf"
  },
  {
    "raw case info": "United States v. California, 432 U.S. 40 (1977).",
    "name": "United States v. California",
    "citation": "432 U.S. 40",
    "year": "1977",
    "url": "https://tile.loc.gov/storage-services/service/ll/usrep/usrep432/usrep432040/usrep432040.pdf"
  },
  {
    "raw case info": "National Socialist Party v. Skokie, 432 U.S. 43 (1977).",
    "name": "National Socialist Party v. Skokie",
    "citation": "432 U.S. 43",
    "year": "1977",
    "url": "https://tile.loc.gov/storage-services/service/ll/usrep/usrep432/usrep432043/usrep432043.pdf"
  },
  {
    "raw case info": "E. I. du Pont de Nemours &amp; Co. v. Collins, 432 U.S. 46 (1977).",
    "name": "E. I. du Pont de Nemours &amp; Co. v. Collins",
    "citation": "432 U.S. 46",
    "year": "1977",
    "url": "https://tile.loc.gov/storage-services/service/ll/usrep/usrep432/usrep432046/usrep432046.pdf"
  },
  {
    "raw case info": "Trans World Airlines, Inc. v. Hardison, 432 U.S. 63 (1977).",
    "name": "Trans World Airlines, Inc. v. Hardison",
    "citation": "432 U.S. 63",
    "year": "1977",
    "url": "https://tile.loc.gov/storage-services/service/ll/usrep/usrep432/usrep432063/usrep432063.pdf"
  },
  {
    "raw case info": "Manson v. Brathwaite, 432 U.S. 98 (1977).",
    "name": "Manson v. Brathwaite",
    "citation": "432 U.S. 98",
    "year": "1977",
    "url": "https://tile.loc.gov/storage-services/service/ll/usrep/usrep432/usrep432098/usrep432098.pdf"
  },
  {
    "raw case info": "Jeffers v. United States, 432 U.S. 137 (1977).",
    "name": "Jeffers v. United States",
    "citation": "432 U.S. 137",
    "year": "1977",
    "url": "https://tile.loc.gov/storage-services/service/ll/usrep/usrep432/usrep432137/usrep432137.pdf"
  },
  {
    "raw case info": "Brown v. Ohio, 432 U.S. 161 (1977).",
    "name": "Brown v. Ohio",
    "citation": "432 U.S. 161",
    "year": "1977",
    "url": "https://tile.loc.gov/storage-services/service/ll/usrep/usrep432/usrep432161/usrep432161.pdf"
  },
  {
    "raw case info": "Mandel v. Bradley, 432 U.S. 173 (1977).",
    "name": "Mandel v. Bradley",
    "citation": "432 U.S. 173",
    "year": "1977",
    "url": "https://tile.loc.gov/storage-services/service/ll/usrep/usrep432/usrep432173/usrep432173.pdf"
  },
  {
    "raw case info": "Jones v. Hildebrant, 432 U.S. 183 (1977).",
    "name": "Jones v. Hildebrant",
    "citation": "432 U.S. 183",
    "year": "1977",
    "url": "https://tile.loc.gov/storage-services/service/ll/usrep/usrep432/usrep432183/usrep432183.pdf"
  },
  {
    "raw case info": "Patterson v. New York, 432 U.S. 197 (1977).",
    "name": "Patterson v. New York",
    "citation": "432 U.S. 197",
    "year": "1977",
    "url": "https://tile.loc.gov/storage-services/service/ll/usrep/usrep432/usrep432197/usrep432197.pdf"
  },
  {
    "raw case info": "Hankerson v. North Carolina, 432 U.S. 233 (1977).",
    "name": "Hankerson v. North Carolina",
    "citation": "432 U.S. 233",
    "year": "1977",
    "url": "https://tile.loc.gov/storage-services/service/ll/usrep/usrep432/usrep432233/usrep432233.pdf"
  },
  {
    "raw case info": "Northeast Marine Terminal Co. v. Caputo, 432 U.S. 249 (1977).",
    "name": "Northeast Marine Terminal Co. v. Caputo",
    "citation": "432 U.S. 249",
    "year": "1977",
    "url": "https://tile.loc.gov/storage-services/service/ll/usrep/usrep432/usrep432249/usrep432249.pdf"
  },
  {
    "raw case info": "Dobbert v. Florida, 432 U.S. 282 (1977).",
    "name": "Dobbert v. Florida",
    "citation": "432 U.S. 282",
    "year": "1977",
    "url": "https://tile.loc.gov/storage-services/service/ll/usrep/usrep432/usrep432282/usrep432282.pdf"
  },
  {
    "raw case info": "Third National Bank v. Impac Limited, Inc., 432 U.S. 312 (1977).",
    "name": "Third National Bank v. Impac Limited, Inc.",
    "citation": "432 U.S. 312",
    "year": "1977",
    "url": "https://tile.loc.gov/storage-services/service/ll/usrep/usrep432/usrep432312/usrep432312.pdf"
  },
  {
    "raw case info": "Hunt v. Washington Apple Advertising Comm'n, 432 U.S. 333 (1977).",
    "name": "Hunt v. Washington Apple Advertising Comm'n",
    "citation": "432 U.S. 333",
    "year": "1977",
    "url": "https://tile.loc.gov/storage-services/service/ll/usrep/usrep432/usrep432333/usrep432333.pdf"
  },
  {
    "raw case info": "Occidental Life Ins. Co. v. EEOC, 432 U.S. 355 (1977).",
    "name": "Occidental Life Ins. Co. v. EEOC",
    "citation": "432 U.S. 355",
    "year": "1977",
    "url": "https://tile.loc.gov/storage-services/service/ll/usrep/usrep432/usrep432355/usrep432355.pdf"
  },
  {
    "raw case info": "United Airlines, Inc. v. McDonald, 432 U.S. 385 (1977).",
    "name": "United Airlines, Inc. v. McDonald",
    "citation": "432 U.S. 385",
    "year": "1977",
    "url": "https://tile.loc.gov/storage-services/service/ll/usrep/usrep432/usrep432385/usrep432385.pdf"
  },
  {
    "raw case info": "Briscoe v. Bell, 432 U.S. 404 (1977).",
    "name": "Briscoe v. Bell",
    "citation": "432 U.S. 404",
    "year": "1977",
    "url": "https://tile.loc.gov/storage-services/service/ll/usrep/usrep432/usrep432404/usrep432404.pdf"
  },
  {
    "raw case info": "Morales v. Turman, 430 U.S. 322 (1977).",
    "name": "Morales v. Turman",
    "citation": "430 U.S. 322",
    "year": "1977",
    "url": "https://tile.loc.gov/storage-services/service/ll/usrep/usrep430/usrep430322/usrep430322.pdf"
  },
  {
    "raw case info": "Costello v. Wainwright, 430 U.S. 325 (1977).",
    "name": "Costello v. Wainwright",
    "citation": "430 U.S. 325",
    "year": "1977",
    "url": "https://tile.loc.gov/storage-services/service/ll/usrep/usrep430/usrep430325/usrep430325.pdf"
  },
  {
    "raw case info": "Juidice v. Vail, 430 U.S. 327 (1977).",
    "name": "Juidice v. Vail",
    "citation": "430 U.S. 327",
    "year": "1977",
    "url": "https://tile.loc.gov/storage-services/service/ll/usrep/usrep430/usrep430327/usrep430327.pdf"
  },
  {
    "raw case info": "Gardner v. Florida, 430 U.S. 349 (1977).",
    "name": "Gardner v. Florida",
    "citation": "430 U.S. 349",
    "year": "1977",
    "url": "https://tile.loc.gov/storage-services/service/ll/usrep/usrep430/usrep430349/usrep430349.pdf"
  },
  {
    "raw case info": "Swain v. Pressley, 430 U.S. 372 (1977).",
    "name": "Swain v. Pressley",
    "citation": "430 U.S. 372",
    "year": "1977",
    "url": "https://tile.loc.gov/storage-services/service/ll/usrep/usrep430/usrep430372/usrep430372.pdf"
  },
  {
    "raw case info": "Brewer v. Williams, 430 U.S. 387 (1977).",
    "name": "Brewer v. Williams",
    "citation": "430 U.S. 387",
    "year": "1977",
    "url": "https://tile.loc.gov/storage-services/service/ll/usrep/usrep430/usrep430387/usrep430387.pdf"
  },
  {
    "raw case info": "Atlas Roofing Co. v. Occupational Safety Comm'n, 430 U.S. 442 (1977).",
    "name": "Atlas Roofing Co. v. Occupational Safety Comm'n",
    "citation": "430 U.S. 442",
    "year": "1977",
    "url": "https://tile.loc.gov/storage-services/service/ll/usrep/usrep430/usrep430442/usrep430442.pdf"
  },
  {
    "raw case info": "Santa Fe Industries, Inc. v. Green, 430 U.S. 462 (1977).",
    "name": "Santa Fe Industries, Inc. v. Green",
    "citation": "430 U.S. 462",
    "year": "1977",
    "url": "https://tile.loc.gov/storage-services/service/ll/usrep/usrep430/usrep430462/usrep430462.pdf"
  },
  {
    "raw case info": "Castaneda v. Partida, 430 U.S. 482 (1977).",
    "name": "Castaneda v. Partida",
    "citation": "430 U.S. 482",
    "year": "1977",
    "url": "https://tile.loc.gov/storage-services/service/ll/usrep/usrep430/usrep430482/usrep430482.pdf"
  },
  {
    "raw case info": "Jones v. Rath Packing Co., 430 U.S. 519 (1977).",
    "name": "Jones v. Rath Packing Co.",
    "citation": "430 U.S. 519",
    "year": "1977",
    "url": "https://tile.loc.gov/storage-services/service/ll/usrep/usrep430/usrep430519/usrep430519.pdf"
  },
  {
    "raw case info": "Maness v. Wainwright, Secretary, Department of Offender Rehabilitation of Florida, 430 U.S. 550 (1977).",
    "name": "Maness v. Wainwright, Secretary, Department of Offender Rehabilitation of Florida",
    "citation": "430 U.S. 550",
    "year": "1977",
    "url": "https://tile.loc.gov/storage-services/service/ll/usrep/usrep430/usrep430550/usrep430550.pdf"
  },
  {
    "raw case info": "National Geographic v. Cal. Equalization Bd., 430 U.S. 551 (1977).",
    "name": "National Geographic v. Cal. Equalization Bd.",
    "citation": "430 U.S. 551",
    "year": "1977",
    "url": "https://tile.loc.gov/storage-services/service/ll/usrep/usrep430/usrep430551/usrep430551.pdf"
  },
  {
    "raw case info": "United States v. Martin Linen Supply Co., 430 U.S. 564 (1977).",
    "name": "United States v. Martin Linen Supply Co.",
    "citation": "430 U.S. 564",
    "year": "1977",
    "url": "https://tile.loc.gov/storage-services/service/ll/usrep/usrep430/usrep430564/usrep430564.pdf"
  },
  {
    "raw case info": "Rosebud Sioux Tribe v. Kneip, 430 U.S. 584 (1977).",
    "name": "Rosebud Sioux Tribe v. Kneip",
    "citation": "430 U.S. 584",
    "year": "1977",
    "url": "https://tile.loc.gov/storage-services/service/ll/usrep/usrep430/usrep430584/usrep430584.pdf"
  },
  {
    "raw case info": "Alexander v. Fioto, 430 U.S. 634 (1977).",
    "name": "Alexander v. Fioto",
    "citation": "430 U.S. 634",
    "year": "1977",
    "url": "https://tile.loc.gov/storage-services/service/ll/usrep/usrep430/usrep430634/usrep430634.pdf"
  },
  {
    "raw case info": "United States v. Antelope, 430 U.S. 641 (1977).",
    "name": "United States v. Antelope",
    "citation": "430 U.S. 641",
    "year": "1977",
    "url": "https://tile.loc.gov/storage-services/service/ll/usrep/usrep430/usrep430641/usrep430641.pdf"
  },
  {
    "raw case info": "Ingraham v. Wright, 430 U.S. 651 (1977).",
    "name": "Ingraham v. Wright",
    "citation": "430 U.S. 651",
    "year": "1977",
    "url": "https://tile.loc.gov/storage-services/service/ll/usrep/usrep430/usrep430651/usrep430651.pdf"
  },
  {
    "raw case info": "Vorchheimer v. School District of Philadelphia, 430 U.S. 703 (1977).",
    "name": "Vorchheimer v. School District of Philadelphia",
    "citation": "430 U.S. 703",
    "year": "1977",
    "url": "https://tile.loc.gov/storage-services/service/ll/usrep/usrep430/usrep430703/usrep430703.pdf"
  },
  {
    "raw case info": "Darden v. Florida, 430 U.S. 704 (1977).",
    "name": "Darden v. Florida",
    "citation": "430 U.S. 704",
    "year": "1977",
    "url": "https://tile.loc.gov/storage-services/service/ll/usrep/usrep430/usrep430704/usrep430704.pdf"
  },
  {
    "raw case info": "Wooley v. Maynard, 430 U.S. 705 (1977).",
    "name": "Wooley v. Maynard",
    "citation": "430 U.S. 705",
    "year": "1977",
    "url": "https://tile.loc.gov/storage-services/service/ll/usrep/usrep430/usrep430705/usrep430705.pdf"
  },
  {
    "raw case info": "Gravitt v. Southwestern Bell Telephone Co., 430 U.S. 723 (1977).",
    "name": "Gravitt v. Southwestern Bell Telephone Co.",
    "citation": "430 U.S. 723",
    "year": "1977",
    "url": "https://tile.loc.gov/storage-services/service/ll/usrep/usrep430/usrep430723/usrep430723.pdf"
  },
  {
    "raw case info": "United States v. Consumer Life Ins. Co., 430 U.S. 725 (1977).",
    "name": "United States v. Consumer Life Ins. Co.",
    "citation": "430 U.S. 725",
    "year": "1977",
    "url": "https://tile.loc.gov/storage-services/service/ll/usrep/usrep430/usrep430725/usrep430725.pdf"
  },
  {
    "raw case info": "Trimble v. Gordon, 430 U.S. 762 (1977).",
    "name": "Trimble v. Gordon",
    "citation": "430 U.S. 762",
    "year": "1977",
    "url": "https://tile.loc.gov/storage-services/service/ll/usrep/usrep430/usrep430762/usrep430762.pdf"
  },
  {
    "raw case info": "Fiallo v. Bell, 430 U.S. 787 (1977).",
    "name": "Fiallo v. Bell",
    "citation": "430 U.S. 787",
    "year": "1977",
    "url": "https://tile.loc.gov/storage-services/service/ll/usrep/usrep430/usrep430787/usrep430787.pdf"
  },
  {
    "raw case info": "Bounds v. Smith, 430 U.S. 817 (1977).",
    "name": "Bounds v. Smith",
    "citation": "430 U.S. 817",
    "year": "1977",
    "url": "https://tile.loc.gov/storage-services/service/ll/usrep/usrep430/usrep430817/usrep430817.pdf"
  },
  {
    "raw case info": "United States Trust Co. v. New Jersey, 431 U.S. 1 (1977).",
    "name": "United States Trust Co. v. New Jersey",
    "citation": "431 U.S. 1",
    "year": "1977",
    "url": "https://tile.loc.gov/storage-services/service/ll/usrep/usrep431/usrep431001/usrep431001.pdf"
  },
  {
    "raw case info": "Blackledge v. Allison, 431 U.S. 63 (1977).",
    "name": "Blackledge v. Allison",
    "citation": "431 U.S. 63",
    "year": "1977",
    "url": "https://tile.loc.gov/storage-services/service/ll/usrep/usrep431/usrep431063/usrep431063.pdf"
  },
  {
    "raw case info": "Linmark Associates, Inc. v. Willingboro, 431 U.S. 85 (1977).",
    "name": "Linmark Associates, Inc. v. Willingboro",
    "citation": "431 U.S. 85",
    "year": "1977",
    "url": "https://tile.loc.gov/storage-services/service/ll/usrep/usrep431/usrep431085/usrep431085.pdf"
  },
  {
    "raw case info": "EPA v. Brown, 431 U.S. 99 (1977).",
    "name": "EPA v. Brown",
    "citation": "431 U.S. 99",
    "year": "1977",
    "url": "https://tile.loc.gov/storage-services/service/ll/usrep/usrep431/usrep431099/usrep431099.pdf"
  },
  {
    "raw case info": "Dixon v. Love, 431 U.S. 105 (1977).",
    "name": "Dixon v. Love",
    "citation": "431 U.S. 105",
    "year": "1977",
    "url": "https://tile.loc.gov/storage-services/service/ll/usrep/usrep431/usrep431105/usrep431105.pdf"
  },
  {
    "raw case info": "Kremens v. Bartley, 431 U.S. 119 (1977).",
    "name": "Kremens v. Bartley",
    "citation": "431 U.S. 119",
    "year": "1977",
    "url": "https://tile.loc.gov/storage-services/service/ll/usrep/usrep431/usrep431119/usrep431119.pdf"
  },
  {
    "raw case info": "Henderson v. Kibbe, 431 U.S. 145 (1977).",
    "name": "Henderson v. Kibbe",
    "citation": "431 U.S. 145",
    "year": "1977",
    "url": "https://tile.loc.gov/storage-services/service/ll/usrep/usrep431/usrep431145/usrep431145.pdf"
  },
  {
    "raw case info": "Chappelle v. Greater Baton Rouge Airport Dist., 431 U.S. 159 (1977).",
    "name": "Chappelle v. Greater Baton Rouge Airport Dist.",
    "citation": "431 U.S. 159",
    "year": "1977",
    "url": "https://tile.loc.gov/storage-services/service/ll/usrep/usrep431/usrep431159/usrep431159.pdf"
  },
  {
    "raw case info": "Texas v. Louisiana, 431 U.S. 161 (1976).",
    "name": "Texas v. Louisiana",
    "citation": "431 U.S. 161",
    "year": "1976",
    "url": "https://tile.loc.gov/storage-services/service/ll/usrep/usrep431/usrep431161/usrep431161.pdf"
  },
  {
    "raw case info": "Pressler v. Blumenthal, 431 U.S. 169 (1977).",
    "name": "Pressler v. Blumenthal",
    "citation": "431 U.S. 169",
    "year": "1977",
    "url": "https://tile.loc.gov/storage-services/service/ll/usrep/usrep431/usrep431169/usrep431169.pdf"
  },
  {
    "raw case info": "Ashcroft v. Mattis, 431 U.S. 171 (1977).",
    "name": "Ashcroft v. Mattis",
    "citation": "431 U.S. 171",
    "year": "1977",
    "url": "https://tile.loc.gov/storage-services/service/ll/usrep/usrep431/usrep431171/usrep431171.pdf"
  },
  {
    "raw case info": "United States v. Wong, 431 U.S. 174 (1977).",
    "name": "United States v. Wong",
    "citation": "431 U.S. 174",
    "year": "1977",
    "url": "https://tile.loc.gov/storage-services/service/ll/usrep/usrep431/usrep431174/usrep431174.pdf"
  },
  {
    "raw case info": "United States v. Washington, 431 U.S. 181 (1977).",
    "name": "United States v. Washington",
    "citation": "431 U.S. 181",
    "year": "1977",
    "url": "https://tile.loc.gov/storage-services/service/ll/usrep/usrep431/usrep431181/usrep431181.pdf"
  },
  {
    "raw case info": "Guam v. Olsen, 431 U.S. 195 (1977).",
    "name": "Guam v. Olsen",
    "citation": "431 U.S. 195",
    "year": "1977",
    "url": "https://tile.loc.gov/storage-services/service/ll/usrep/usrep431/usrep431195/usrep431195.pdf"
  },
  {
    "raw case info": "Abood v. Detroit Board of Education, 431 U.S. 209 (1977).",
    "name": "Abood v. Detroit Board of Education",
    "citation": "431 U.S. 209",
    "year": "1977",
    "url": "https://tile.loc.gov/storage-services/service/ll/usrep/usrep431/usrep431209/usrep431209.pdf"
  },
  {
    "raw case info": "Smith v. United States, 431 U.S. 291 (1977).",
    "name": "Smith v. United States",
    "citation": "431 U.S. 291",
    "year": "1977",
    "url": "https://tile.loc.gov/storage-services/service/ll/usrep/usrep431/usrep431291/usrep431291.pdf"
  },
  {
    "raw case info": "Massachusetts v. Westcott, 431 U.S. 322 (1977).",
    "name": "Massachusetts v. Westcott",
    "citation": "431 U.S. 322",
    "year": "1977",
    "url": "https://tile.loc.gov/storage-services/service/ll/usrep/usrep431/usrep431322/usrep431322.pdf"
  },
  {
    "raw case info": "Teamsters v. United States, 431 U.S. 324 (1977).",
    "name": "Teamsters v. United States",
    "citation": "431 U.S. 324",
    "year": "1977",
    "url": "https://tile.loc.gov/storage-services/service/ll/usrep/usrep431/usrep431324/usrep431324.pdf"
  },
  {
    "raw case info": "East Texas Motor Freight v. Rodriguez, 431 U.S. 395 (1977).",
    "name": "East Texas Motor Freight v. Rodriguez",
    "citation": "431 U.S. 395",
    "year": "1977",
    "url": "https://tile.loc.gov/storage-services/service/ll/usrep/usrep431/usrep431395/usrep431395.pdf"
  },
  {
    "raw case info": "Connor v. Finch, 431 U.S. 407 (1977).",
    "name": "Connor v. Finch",
    "citation": "431 U.S. 407",
    "year": "1977",
    "url": "https://tile.loc.gov/storage-services/service/ll/usrep/usrep431/usrep431407/usrep431407.pdf"
  },
  {
    "raw case info": "Trainor v. Hernandez, 431 U.S. 434 (1977).",
    "name": "Trainor v. Hernandez",
    "citation": "431 U.S. 434",
    "year": "1977",
    "url": "https://tile.loc.gov/storage-services/service/ll/usrep/usrep431/usrep431434/usrep431434.pdf"
  },
  {
    "raw case info": "Ohio Bureau of Employment Services v. Hodory, 431 U.S. 471 (1977).",
    "name": "Ohio Bureau of Employment Services v. Hodory",
    "citation": "431 U.S. 471",
    "year": "1977",
    "url": "https://tile.loc.gov/storage-services/service/ll/usrep/usrep431/usrep431471/usrep431471.pdf"
  },
  {
    "raw case info": "Moore v. East Cleveland, 431 U.S. 494 (1977).",
    "name": "Moore v. East Cleveland",
    "citation": "431 U.S. 494",
    "year": "1977",
    "url": "https://tile.loc.gov/storage-services/service/ll/usrep/usrep431/usrep431494/usrep431494.pdf"
  },
  {
    "raw case info": "United Air Lines, Inc. v. Evans, 431 U.S. 553 (1977).",
    "name": "United Air Lines, Inc. v. Evans",
    "citation": "431 U.S. 553",
    "year": "1977",
    "url": "https://tile.loc.gov/storage-services/service/ll/usrep/usrep431/usrep431553/usrep431553.pdf"
  },
  {
    "raw case info": "Scarborough v. United States, 431 U.S. 563 (1977).",
    "name": "Scarborough v. United States",
    "citation": "431 U.S. 563",
    "year": "1977",
    "url": "https://tile.loc.gov/storage-services/service/ll/usrep/usrep431/usrep431563/usrep431563.pdf"
  },
  {
    "raw case info": "Alabama Power Co. v. Davis, 431 U.S. 581 (1977).",
    "name": "Alabama Power Co. v. Davis",
    "citation": "431 U.S. 581",
    "year": "1977",
    "url": "https://tile.loc.gov/storage-services/service/ll/usrep/usrep431/usrep431581/usrep431581.pdf"
  },
  {
    "raw case info": "Splawn v. California, 431 U.S. 595 (1977).",
    "name": "Splawn v. California",
    "citation": "431 U.S. 595",
    "year": "1977",
    "url": "https://tile.loc.gov/storage-services/service/ll/usrep/usrep431/usrep431595/usrep431595.pdf"
  },
  {
    "raw case info": "United States v. Ramsey, 431 U.S. 606 (1977).",
    "name": "United States v. Ramsey",
    "citation": "431 U.S. 606",
    "year": "1977",
    "url": "https://tile.loc.gov/storage-services/service/ll/usrep/usrep431/usrep431606/usrep431606.pdf"
  },
  {
    "raw case info": "Roberts v. Louisiana, 431 U.S. 633 (1977).",
    "name": "Roberts v. Louisiana",
    "citation": "431 U.S. 633",
    "year": "1977",
    "url": "https://tile.loc.gov/storage-services/service/ll/usrep/usrep431/usrep431633/usrep431633.pdf"
  },
  {
    "raw case info": "Abney v. United States, 431 U.S. 651 (1977).",
    "name": "Abney v. United States",
    "citation": "431 U.S. 651",
    "year": "1977",
    "url": "https://tile.loc.gov/storage-services/service/ll/usrep/usrep431/usrep431651/usrep431651.pdf"
  },
  {
    "raw case info": "Stencel Aero Engineering Corp v. U.S., 431 U.S. 666 (1977).",
    "name": "Stencel Aero Engineering Corp v. U.S.",
    "citation": "431 U.S. 666",
    "year": "1977",
    "url": "https://tile.loc.gov/storage-services/service/ll/usrep/usrep431/usrep431666/usrep431666.pdf"
  },
  {
    "raw case info": "Carey v. Population Services International, 431 U.S. 678 (1977).",
    "name": "Carey v. Population Services International",
    "citation": "431 U.S. 678",
    "year": "1977",
    "url": "https://tile.loc.gov/storage-services/service/ll/usrep/usrep431/usrep431678/usrep431678.pdf"
  },
  {
    "raw case info": "Illinois Brick Co. v. Illinois, 431 U.S. 720 (1977).",
    "name": "Illinois Brick Co. v. Illinois",
    "citation": "431 U.S. 720",
    "year": "1977",
    "url": "https://tile.loc.gov/storage-services/service/ll/usrep/usrep431/usrep431720/usrep431720.pdf"
  },
  {
    "raw case info": "Ward v. Illinois, 431 U.S. 767 (1977).",
    "name": "Ward v. Illinois",
    "citation": "431 U.S. 767",
    "year": "1977",
    "url": "https://tile.loc.gov/storage-services/service/ll/usrep/usrep431/usrep431767/usrep431767.pdf"
  },
  {
    "raw case info": "United States v. Lovasco, 431 U.S. 783 (1977).",
    "name": "United States v. Lovasco",
    "citation": "431 U.S. 783",
    "year": "1977",
    "url": "https://tile.loc.gov/storage-services/service/ll/usrep/usrep431/usrep431783/usrep431783.pdf"
  },
  {
    "raw case info": "Lefkowitz v. Cunningham, 431 U.S. 801 (1977).",
    "name": "Lefkowitz v. Cunningham",
    "citation": "431 U.S. 801",
    "year": "1977",
    "url": "https://tile.loc.gov/storage-services/service/ll/usrep/usrep431/usrep431801/usrep431801.pdf"
  },
  {
    "raw case info": "Batterton v. Francis, 432 U.S. 416 (1977).",
    "name": "Batterton v. Francis",
    "citation": "432 U.S. 416",
    "year": "1977",
    "url": "https://tile.loc.gov/storage-services/service/ll/usrep/usrep432/usrep432416/usrep432416.pdf"
  },
  {
    "raw case info": "Beal v. Doe, 432 U.S. 438 (1977).",
    "name": "Beal v. Doe",
    "citation": "432 U.S. 438",
    "year": "1977",
    "url": "https://tile.loc.gov/storage-services/service/ll/usrep/usrep432/usrep432438/usrep432438.pdf"
  },
  {
    "raw case info": "Maher v. Roe, 432 U.S. 464 (1977).",
    "name": "Maher v. Roe",
    "citation": "432 U.S. 464",
    "year": "1977",
    "url": "https://tile.loc.gov/storage-services/service/ll/usrep/usrep432/usrep432464/usrep432464.pdf"
  },
  {
    "raw case info": "Morris v. Gressette., 432 U.S. 491 (1977).",
    "name": "Morris v. Gressette.",
    "citation": "432 U.S. 491",
    "year": "1977",
    "url": "https://tile.loc.gov/storage-services/service/ll/usrep/usrep432/usrep432491/usrep432491.pdf"
  },
  {
    "raw case info": "Poelker v. Doe, 432 U.S. 519 (1977).",
    "name": "Poelker v. Doe",
    "citation": "432 U.S. 519",
    "year": "1977",
    "url": "https://tile.loc.gov/storage-services/service/ll/usrep/usrep432/usrep432519/usrep432519.pdf"
  },
  {
    "raw case info": "Maher v. Doe, 432 U.S. 526 (1977).",
    "name": "Maher v. Doe",
    "citation": "432 U.S. 526",
    "year": "1977",
    "url": "https://tile.loc.gov/storage-services/service/ll/usrep/usrep432/usrep432526/usrep432526.pdf"
  },
  {
    "raw case info": "United States v. Chadwick, 433 U.S. 1 (1977).",
    "name": "United States v. Chadwick",
    "citation": "433 U.S. 1",
    "year": "1977",
    "url": "https://tile.loc.gov/storage-services/service/ll/usrep/usrep433/usrep433001/usrep433001.pdf"
  },
  {
    "raw case info": "Miree v. DeKalb County, 433 U.S. 25 (1977).",
    "name": "Miree v. DeKalb County",
    "citation": "433 U.S. 25",
    "year": "1977",
    "url": "https://tile.loc.gov/storage-services/service/ll/usrep/usrep433/usrep433025/usrep433025.pdf"
  },
  {
    "raw case info": "Continental T. V., Inc. v. GTE Sylvania Inc., 433 U.S. 36 (1977).",
    "name": "Continental T. V., Inc. v. GTE Sylvania Inc.",
    "citation": "433 U.S. 36",
    "year": "1977",
    "url": "https://tile.loc.gov/storage-services/service/ll/usrep/usrep433/usrep433036/usrep433036.pdf"
  },
  {
    "raw case info": "Wainwright v. Sykes, 433 U.S. 72 (1977).",
    "name": "Wainwright v. Sykes",
    "citation": "433 U.S. 72",
    "year": "1977",
    "url": "https://tile.loc.gov/storage-services/service/ll/usrep/usrep433/usrep433072/usrep433072.pdf"
  },
  {
    "raw case info": "Commissioner v. Standard Life &amp; Acc. Ins. Co., 433 U.S. 148 (1977).",
    "name": "Commissioner v. Standard Life &amp; Acc. Ins. Co.",
    "citation": "433 U.S. 148",
    "year": "1977",
    "url": "https://tile.loc.gov/storage-services/service/ll/usrep/usrep433/usrep433148/usrep433148.pdf"
  },
  {
    "raw case info": "Puyallup Tribe v. Washington Game Dept., 433 U.S. 165 (1977).",
    "name": "Puyallup Tribe v. Washington Game Dept.",
    "citation": "433 U.S. 165",
    "year": "1977",
    "url": "https://tile.loc.gov/storage-services/service/ll/usrep/usrep433/usrep433165/usrep433165.pdf"
  }
]
